docker_tui/__init__.py
docker_tui/app.py
docker_tui/docker_client.py
dockerdt-0.2.0.dist-info/METADATA
dockerdt-0.2.0.dist-info/WHEEL
dockerdt-0.2.0.dist-info/entry_points.txt
dockerdt-0.2.0.dist-info/licenses/LICENSE
dockerdt-0.2.0.dist-info/RECORD
