Metadata-Version: 2.4
Name: dockerdt
Version: 0.2.0
Summary: A beautiful TUI for managing Docker containers
Project-URL: Homepage, https://github.com/rstar327/docker-tui
Project-URL: Repository, https://github.com/rstar327/docker-tui
Author-email: rstar327 <rockstar00327@outlook.com>
License-Expression: MIT
License-File: LICENSE
Keywords: containers,dashboard,docker,terminal,tui
Classifier: Development Status :: 4 - Beta
Classifier: Environment :: Console
Classifier: Environment :: Console :: Curses
Classifier: Intended Audience :: Developers
Classifier: Intended Audience :: System Administrators
Classifier: License :: OSI Approved :: MIT License
Classifier: Operating System :: MacOS
Classifier: Operating System :: OS Independent
Classifier: Operating System :: POSIX :: Linux
Classifier: Programming Language :: Python :: 3
Classifier: Programming Language :: Python :: 3.10
Classifier: Programming Language :: Python :: 3.11
Classifier: Programming Language :: Python :: 3.12
Classifier: Programming Language :: Python :: 3.13
Classifier: Topic :: Software Development :: User Interfaces
Classifier: Topic :: System :: Monitoring
Classifier: Topic :: System :: Systems Administration
Classifier: Topic :: Utilities
Requires-Python: >=3.10
Requires-Dist: docker>=7.0.0
Requires-Dist: rich>=13.0
Requires-Dist: textual>=0.47.0
Provides-Extra: dev
Requires-Dist: black; extra == 'dev'
Requires-Dist: pytest>=7.0; extra == 'dev'
Requires-Dist: ruff; extra == 'dev'
